tests/__init__.py
tests/test_ek0.py
tests/test_ek1.py
tests/test_init.py
tests/test_ivp.py
tests/test_iwp.py
tests/test_kalman.py
tests/test_odefilter.py
tests/test_rv.py
tests/test_sqrt.py
tests/test_step.py
tests/experimental/__init__.py
tests/experimental/test_enkf.py
tests/experimental/test_linops.py
tests/experimental/test_truncated.py
tornadox/__init__.py
tornadox/_version.py
tornadox/ek0.py
tornadox/ek1.py
tornadox/init.py
tornadox/ivp.py
tornadox/iwp.py
tornadox/kalman.py
tornadox/odefilter.py
tornadox/rv.py
tornadox/sqrt.py
tornadox/step.py
tornadox/experimental/__init__.py
tornadox/experimental/enkf.py
tornadox/experimental/linops.py
tornadox/experimental/truncated.py
tornadox-0.0.2.dist-info/LICENSE
tornadox-0.0.2.dist-info/METADATA
tornadox-0.0.2.dist-info/WHEEL
tornadox-0.0.2.dist-info/top_level.txt
tornadox-0.0.2.dist-info/RECORD
