Metadata-Version: 2.1
Name: tornadox
Version: 0.0.2
Author: Nicholas Krämer, Nathanael Bosch, Jonathan Schmidt
License: MIT
Requires-Python: >=3.8
License-File: LICENSE
Requires-Dist: numpy
Requires-Dist: scipy
Requires-Dist: tqdm
Requires-Dist: jax
Requires-Dist: jaxlib
Provides-Extra: contrib
Requires-Dist: pytest ; extra == 'contrib'
Requires-Dist: pylint ; extra == 'contrib'
Requires-Dist: black (>=22.1) ; extra == 'contrib'
Requires-Dist: isort ; extra == 'contrib'
